petscii_codecs/__init__.py
petscii_codecs/petscii_40c128_uc.py
petscii_codecs/petscii_40c128en_lc.py
petscii_codecs/petscii_40c128en_uc.py
petscii_codecs/petscii_80c128en_lc.py
petscii_codecs/petscii_80c128en_uc.py
petscii_codecs/petscii_c16en_lc.py
petscii_codecs/petscii_c16en_uc.py
petscii_codecs/petscii_c64en_lc.py
petscii_codecs/petscii_c64en_uc.py
petscii_codecs/petscii_pet2001en_lc.py
petscii_codecs/petscii_pet2001en_uc.py
petscii_codecs/petscii_peten_lc.py
petscii_codecs/petscii_peten_uc.py
petscii_codecs/petscii_vic1001jp_gr.py
petscii_codecs/petscii_vic1001jp_kk.py
petscii_codecs/petscii_vic20en_lc.py
petscii_codecs/petscii_vic20en_uc.py
petscii_codecs-2.1.dist-info/LICENSE.txt
petscii_codecs-2.1.dist-info/METADATA
petscii_codecs-2.1.dist-info/WHEEL
petscii_codecs-2.1.dist-info/top_level.txt
petscii_codecs-2.1.dist-info/RECORD
