Metadata-Version: 2.1
Name: petscii-codecs
Version: 2.1
Summary: Python codecs for PETSCII character sets
Home-page: https://eden.mose.org.uk/gitweb/?p=petscii-codecs.git
Author: Simon Rowe
Author-email: srowe@mose.org.uk
License: GPLv2
Classifier: Development Status :: 5 - Production/Stable
Classifier: Intended Audience :: Developers
Classifier: License :: OSI Approved :: GNU General Public License v2 (GPLv2)
Classifier: Programming Language :: Python :: 3
Classifier: Topic :: Software Development :: Libraries :: Python Modules
License-File: LICENSE.txt
